dockswap/__init__.py
dockswap/cli.py
dockswap/dockswap/__init__.py
dockswap/dockswap/core.py
dockswap/dockswap/errors.py
dockswap/dockswap/validators.py
dockswap-0.3.0.dist-info/AUTHORS.rst
dockswap-0.3.0.dist-info/LICENSE
dockswap-0.3.0.dist-info/METADATA
dockswap-0.3.0.dist-info/WHEEL
dockswap-0.3.0.dist-info/entry_points.txt
dockswap-0.3.0.dist-info/top_level.txt
dockswap-0.3.0.dist-info/RECORD
