Metadata-Version: 2.1
Name: dockswap
Version: 0.3.0
Summary: Tool for easier switching between projects that uses docker containers to set up working environment
Home-page: https://github.com/VagifMammadaliyev/dockswap
Author: Vagif Mammadaliyev
Author-email: vagifmammadaliyev@outlook.com
License: MIT license
Keywords: dockswap
Platform: UNKNOWN
Classifier: Intended Audience :: Developers
Classifier: License :: OSI Approved :: MIT License
Classifier: Programming Language :: Python :: 3
Classifier: Programming Language :: Python :: 3.6
Classifier: Programming Language :: Python :: 3.7
Classifier: Programming Language :: Python :: 3.8
Requires-Python: >=3.6
Requires-Dist: typer (==0.3.2)
